README.md
setup.cfg
setup.py
ahk_distributions.egg-info/PKG-INFO
ahk_distributions.egg-info/SOURCES.txt
ahk_distributions.egg-info/dependency_links.txt
ahk_distributions.egg-info/not-zip-safe
ahk_distributions.egg-info/top_level.txt
distributions/Binomialdistribution.py
distributions/Gaussiandistribution.py
distributions/Generaldistribution.py
distributions/__init__.py