Metadata-Version: 1.0
Name: ahk-distributions
Version: 0.1
Summary: Gaussian distributions
Home-page: UNKNOWN
Author: Aye Hninn Khine
Author-email: ayehninnkhine93@gmail.com
License: UNKNOWN
Platform: UNKNOWN
